number_guess_game/__init__.py
number_guess_game/number_guess_game.py
number_guess_game_2-0.1.0.dist-info/METADATA
number_guess_game_2-0.1.0.dist-info/WHEEL
number_guess_game_2-0.1.0.dist-info/top_level.txt
number_guess_game_2-0.1.0.dist-info/RECORD
