Metadata-Version: 2.4
Name: number_guess_game_2
Version: 0.1.0
Summary: a game that genrates a random number and asks the user to guess it 
Home-page: https://github.com/yourusername/reverseword
Author: Your Name
Author-email: your.email@example.com
Classifier: Programming Language :: Python :: 3
Classifier: License :: OSI Approved :: MIT License
Classifier: Operating System :: OS Independent
Requires-Python: >=3.6
Dynamic: author
Dynamic: author-email
Dynamic: classifier
Dynamic: description
Dynamic: description-content-type
Dynamic: home-page
Dynamic: requires-python
Dynamic: summary
